transllm/__init__.py
transllm/core.py
transllm-0.1.8.dist-info/LICENSE
transllm-0.1.8.dist-info/METADATA
transllm-0.1.8.dist-info/WHEEL
transllm-0.1.8.dist-info/entry_points.txt
transllm-0.1.8.dist-info/top_level.txt
transllm-0.1.8.dist-info/RECORD
