Metadata-Version: 2.1
Name: transllm
Version: 0.1.8
Summary: LLMtranslator translates and generates text in multiple languages.
Home-page: https://github.com/dsdanielpark/hf-transllm
Author: daniel park
Author-email: parkminwoo1991@gmail.com
Keywords: Python,API,Bard,Google Bard,Large Language Model,Chatbot API,Google API,Chatbot
Classifier: Development Status :: 3 - Alpha
Classifier: Intended Audience :: Science/Research
Classifier: Natural Language :: English
Classifier: Programming Language :: Python
Classifier: Programming Language :: Python :: 3.6
Classifier: Programming Language :: Python :: 3.7
Classifier: Programming Language :: Python :: 3.8
Classifier: License :: OSI Approved :: MIT License
Classifier: Programming Language :: Python :: 3.6
Classifier: Topic :: Scientific/Engineering :: Artificial Intelligence
Requires-Python: >=3.6
License-File: LICENSE
Requires-Dist: requests
Requires-Dist: deep-translator
Requires-Dist: colorama
Requires-Dist: httpx[http2]
Requires-Dist: torch
Requires-Dist: deepl
Requires-Dist: transformers
Requires-Dist: bardapi
Requires-Dist: openai
Requires-Dist: sentencepiece
Requires-Dist: accelerate
Requires-Dist: translang
